fel/__init__.py
fel/__main__.py
fel/config.py
fel/land.py
fel/mergeability.py
fel/meta.py
fel/pr.py
fel/rebase.py
fel/stack.py
fel/stack_spinner.py
fel/style.py
fel/submit.py
fel/util.py
fel-0.4.0.dist-info/entry_points.txt
fel-0.4.0.dist-info/LICENSE
fel-0.4.0.dist-info/WHEEL
fel-0.4.0.dist-info/METADATA
fel-0.4.0.dist-info/RECORD
