Metadata-Version: 2.1
Name: fel
Version: 0.4.0
Summary: A tool for submitting and landing stacked diffs to GitHub
Home-page: https://github.com/zabot/fel
License: GPL-3.0-only
Author: Zach Anderson
Author-email: zach.inbox@gmail.com
Requires-Python: >=3.7,<4.0
Classifier: License :: OSI Approved :: GNU General Public License v3 (GPLv3)
Classifier: Programming Language :: Python :: 3
Classifier: Programming Language :: Python :: 3.7
Classifier: Programming Language :: Python :: 3.8
Classifier: Programming Language :: Python :: 3.9
Requires-Dist: GitPython (>=3.1.14,<4.0.0)
Requires-Dist: PyGithub (>=1.55,<2.0)
Requires-Dist: PyYAML (>=5.4.1,<6.0.0)
Requires-Dist: git-filter-repo (>=2.29.0,<3.0.0)
Requires-Dist: yaspin (>=2.0.0,<3.0.0)
Project-URL: Repository, https://github.com/zabot/fel
